qb_parser/__init__.py
qb_parser/answerline_parser.py
qb_parser/clue_tokenizer.py
qb_parser/util.py
qb_parser-0.1.5.dist-info/METADATA
qb_parser-0.1.5.dist-info/WHEEL
qb_parser-0.1.5.dist-info/RECORD
